MANIFEST.in
setup.py
youtube_song_downloader.egg-info/PKG-INFO
youtube_song_downloader.egg-info/SOURCES.txt
youtube_song_downloader.egg-info/dependency_links.txt
youtube_song_downloader.egg-info/entry_points.txt
youtube_song_downloader.egg-info/not-zip-safe
youtube_song_downloader.egg-info/requires.txt
youtube_song_downloader.egg-info/top_level.txt
ytsdl/__init__.py
ytsdl/cli.py
ytsdl/settings.json
ytsdl/songDownloader.py