Metadata-Version: 1.0
Name: youtube-song-downloader
Version: 0.2
Summary: A program used to search and download songs from Youtube.
Home-page: https://github.com/dszopa/youtube-song-downloader
Author: Daniel Szopa
Author-email: dszopa@iastate.edu
License: MIT
Platform: UNKNOWN
